mitm_requests/__init__.py
mitm_requests/addon.py
mitm_requests/capture.py
mitm_requests/proxy.py
mitm_requests-1.0.0.dist-info/METADATA
mitm_requests-1.0.0.dist-info/WHEEL
mitm_requests-1.0.0.dist-info/top_level.txt
mitm_requests-1.0.0.dist-info/RECORD
