Metadata-Version: 2.4
Name: mitm-requests
Version: 1.0.0
Summary: A Python module for intercepting HTTP/HTTPS requests using mitmproxy
Author-email: Leon <leon@example.com>
License: MIT
Project-URL: Homepage, https://github.com/leon/treasure.lgnat.com
Project-URL: Repository, https://github.com/leon/treasure.lgnat.com
Classifier: Development Status :: 4 - Beta
Classifier: Intended Audience :: Developers
Classifier: License :: OSI Approved :: MIT License
Classifier: Programming Language :: Python :: 3
Classifier: Programming Language :: Python :: 3.8
Classifier: Programming Language :: Python :: 3.9
Classifier: Programming Language :: Python :: 3.10
Classifier: Programming Language :: Python :: 3.11
Classifier: Topic :: Internet :: Proxy Servers
Classifier: Topic :: Software Development :: Libraries :: Python Modules
Requires-Python: >=3.8
Requires-Dist: mitmproxy
